{
	"name": "Nguyen Van A",
	"email": "nguyena@gmail.com",
	"phone": "123456789",
	"address": "14 Nguyen Dinh Chieu, Hai Ba Trung, Ha Noi",
	"history": [
		{
			"date": "20/11/2017",
			"total": 457000,
			"subtotal": 457000,
			"shipping": 0,
			"state": "Received",
			"detail": [
				{
					"name": "Icecream 1",
					"count": 2,
					"total": 200000
				},
				{
					"name": "Icecream 2",
					"count": 1,
					"total": 78500
				},
				{
					"name": "Icecream 5",
					"count": 1,
					"total": 178500
				}
			]
		},
		{
			"date": "10/7/2018",
			"total": 100000,
			"subtotal": 100000,
			"shipping": 0,
			"state": "Received",
			"detail": [
				{
					"name": "Icecream 1",
					"count": 1,
					"total": 100000
				}
			]
		}
	]
}